flask_confluent_kafka.py
flask_confluent_kakfa-0.1.0.dist-info/METADATA
flask_confluent_kakfa-0.1.0.dist-info/WHEEL
flask_confluent_kakfa-0.1.0.dist-info/top_level.txt
flask_confluent_kakfa-0.1.0.dist-info/RECORD
