Metadata-Version: 2.4
Name: flask-confluent-kakfa
Version: 0.1.0
Summary: Add your description here
Requires-Python: >=3.13
Requires-Dist: confluent-kafka>=2.11.1
